LICENSE
MANIFEST.in
README.md
setup.cfg
setup.py
cython/glutils.cpp
cython/glutils.hpp
cython/pyhorde.pxd
cython/pyhorde.pyx
docs/Makefile
docs/authors.rst
docs/conf.py
docs/contributing.rst
docs/history.rst
docs/index.rst
docs/installation.rst
docs/make.bat
docs/readme.rst
docs/usage.rst
docs/img/aligned_cubes.jpg
docs/img/animated.gif
docs/img/cube_samples.png
docs/img/example_scene.jpg
docs/img/viewer_box.jpg
docs/img/viewer_empty.jpg
ds2sim/__init__.py
ds2sim/camera.py
ds2sim/data_loader.py
ds2sim/horde.py
ds2sim/logger.py
ds2sim/viewer.py
ds2sim/webserver.py
ds2sim.egg-info/PKG-INFO
ds2sim.egg-info/SOURCES.txt
ds2sim.egg-info/dependency_links.txt
ds2sim.egg-info/not-zip-safe
ds2sim.egg-info/requires.txt
ds2sim.egg-info/top_level.txt
ds2sim/resources/animations/knight_attack.anim
ds2sim/resources/animations/knight_order.anim
ds2sim/resources/animations/man.anim
ds2sim/resources/materials/light.material.xml
ds2sim/resources/models/ball/ball.dae
ds2sim/resources/models/ball/number.jpg
ds2sim/resources/models/cube/cube.geo
ds2sim/resources/models/cube/cube.material.xml
ds2sim/resources/models/cube/cube.scene.xml
ds2sim/resources/models/cube/textures/0.jpg
ds2sim/resources/models/cube/textures/1.jpg
ds2sim/resources/models/cube/textures/2.jpg
ds2sim/resources/models/cube/textures/3.jpg
ds2sim/resources/models/cube/textures/4.jpg
ds2sim/resources/models/cube/textures/5.jpg
ds2sim/resources/models/cube/textures/6.jpg
ds2sim/resources/models/cube/textures/7.jpg
ds2sim/resources/models/cube/textures/8.jpg
ds2sim/resources/models/cube/textures/9.jpg
ds2sim/resources/models/knight/knight.geo
ds2sim/resources/models/knight/knight.jpg
ds2sim/resources/models/knight/knight.material.xml
ds2sim/resources/models/knight/knight.scene.xml
ds2sim/resources/models/man/civil01.jpg
ds2sim/resources/models/man/civilian1.material.xml
ds2sim/resources/models/man/man.geo
ds2sim/resources/models/man/man.scene.xml
ds2sim/resources/models/platform/platform.geo
ds2sim/resources/models/platform/platform.scene.xml
ds2sim/resources/models/platform/stones.material.xml
ds2sim/resources/models/skybox/skybox.dds
ds2sim/resources/models/skybox/skybox.geo
