Metadata-Version: 1.1
Name: ds2sim
Version: 0.5.0
Summary: Fun with Machine Learning and Space Ships
Home-page: https://github.com/olitheolix/ds2sim
Author: Oliver Nagy
Author-email: olitheolix@gmail.com
License: Apache Software License 2.0
Keywords: ds2sim
Platform: UNKNOWN
Classifier: Development Status :: 2 - Pre-Alpha
Classifier: Intended Audience :: Developers
Classifier: License :: OSI Approved :: Apache Software License
Classifier: Natural Language :: English
Classifier: Programming Language :: Python :: 3.6
